dataprofile/__init__.py
dataprofile/dataprofile.py
dataprofile/email_f.py
dataprofile/id_f.py
dataprofile/primary_f.py
dataprofile-1.0.2.dist-info/LICENSE.md
dataprofile-1.0.2.dist-info/METADATA
dataprofile-1.0.2.dist-info/WHEEL
dataprofile-1.0.2.dist-info/top_level.txt
dataprofile-1.0.2.dist-info/RECORD
